pydataconn/README.md
pydataconn/__init__.py
pydataconn/calendar.py
pydataconn/gsheets.py
pydataconn/pyproject.toml
pydataconn/tests/__init__.py
pydataconn/tests/test_calendar.py
pydataconn/tests/test_gsheets.py
pydataconn-0.1.7.dist-info/METADATA
pydataconn-0.1.7.dist-info/WHEEL
pydataconn-0.1.7.dist-info/RECORD
